<annotation>
	<folder>Shaast</folder>
	<filename>30.jpeg</filename>
	<path>C:\Users\shukla\Desktop\Aaditya\Coding\Projects\Python\OpenCV\Computer-Vision\Datasets\Shaast\30.jpeg</path>
	<source>
		<database>Unknown</database>
	</source>
	<size>
		<width>900</width>
		<height>1600</height>
		<depth>3</depth>
	</size>
	<segmented>0</segmented>
	<object>
		<name>Shaast</name>
		<pose>Unspecified</pose>
		<truncated>0</truncated>
		<difficult>0</difficult>
		<bndbox>
			<xmin>198</xmin>
			<ymin>101</ymin>
			<xmax>795</xmax>
			<ymax>828</ymax>
		</bndbox>
	</object>
</annotation>
